Metadata-Version: 1.1
Name: sofine
Version: 0.2.4.2
Summary: Lightweight framework for creating data-collection plugins and chaining together calls to them, from CLI, REST or Python
Home-page: http://packages.python.org/sofine
Author: Mark S. Weiss
Author-email: marksimonweiss@gmail.com
License: MIT
Keywords: glueAPI data pipelines scraper webAPI
Platform: UNKNOWN
Classifier: Development Status :: 3 - Alpha
Classifier: Topic :: Utilities
Classifier: License :: OSI Approved :: MIT License
